poetry_demo/__init__.py
poetry_demo_14-0.2.0.dist-info/METADATA
poetry_demo_14-0.2.0.dist-info/WHEEL
poetry_demo_14-0.2.0.dist-info/RECORD
